README.rst
setup.py
orm/__init__.py
orm/constant.py
orm/log_support.py
orm/orm.py
orm/orm_support.py
orm/snowflake.py
orm/support.py
sqlx_orm.egg-info/PKG-INFO
sqlx_orm.egg-info/SOURCES.txt
sqlx_orm.egg-info/dependency_links.txt
sqlx_orm.egg-info/not-zip-safe
sqlx_orm.egg-info/requires.txt
sqlx_orm.egg-info/top_level.txt