Metadata-Version: 2.1
Name: sqlx-orm
Version: 0.0.3
Summary: A single table ORM framework for python. Support MySQL, PostgreSQL, SQLite etc.
Home-page: https://gitee.com/summry/sqlx-orm
Author: summy
Author-email: xiazhongbiao@126.com
License: UNKNOWN
Keywords: SQL,MySQL,PostgreSQL,SQLite,Oracle,SQL Server,Database,Python,RDB
Platform: UNKNOWN
Requires-Python: >=3.5
